ol_openedx_git_auto_export/__init__.py
ol_openedx_git_auto_export/admin.py
ol_openedx_git_auto_export/app.py
ol_openedx_git_auto_export/constants.py
ol_openedx_git_auto_export/models.py
ol_openedx_git_auto_export/signals.py
ol_openedx_git_auto_export/tasks.py
ol_openedx_git_auto_export/utils.py
ol_openedx_git_auto_export/management/commands/__init__.py
ol_openedx_git_auto_export/management/commands/migrate_giturl.py
ol_openedx_git_auto_export/migrations/0001_initial.py
ol_openedx_git_auto_export/migrations/__init__.py
ol_openedx_git_auto_export/settings/__init__.py
ol_openedx_git_auto_export/settings/common.py
ol_openedx_git_auto_export/settings/production.py
ol_openedx_git_auto_export-0.7.1.dist-info/METADATA
ol_openedx_git_auto_export-0.7.1.dist-info/WHEEL
ol_openedx_git_auto_export-0.7.1.dist-info/entry_points.txt
ol_openedx_git_auto_export-0.7.1.dist-info/licenses/LICENSE
ol_openedx_git_auto_export-0.7.1.dist-info/RECORD
