Metadata-Version: 2.4
Name: ol-openedx-git-auto-export
Version: 0.7.1
Summary: A plugin that auto saves the course OLX to git when an author publishes it
Author: MIT Office of Digital Learning
License-Expression: BSD-3-Clause
License-File: LICENSE
Requires-Python: >=3.11
Requires-Dist: celery>=4.4.7
Requires-Dist: django>=4.0
Requires-Dist: edx-django-utils>4.0.0
Requires-Dist: edx-opaque-keys
Requires-Dist: gitpython>=3.1.37
Requires-Dist: openedx-events
